{
  "configurations": [
    {
      "browse": {
        "databaseFilename": "${default}",
        "limitSymbolsToIncludedHeaders": false
      },
      "includePath": [
        "/home/myk/dev/study/radar/RoLM3.0_zju/devel/include/**",
        "/opt/ros/melodic/include/**",
        "/home/myk/dev/study/radar/RoLM3.0_zju/src/radar_on_lidar_map/include/**",
        "/home/myk/dev/study/radar/RoLM3.0_zju/src/odometry/yeti_radar_odometry/include/**",
        "/usr/include/**"
      ],
      "name": "ROS",
      "intelliSenseMode": "gcc-x64",
      "compilerPath": "/usr/bin/gcc",
      "cStandard": "gnu11",
      "cppStandard": "c++14",
      "compileCommands": "${workspaceFolder}/build/compile_commands.jason"
    }
  ],
  "version": 4
}